 [
  {"id":"1","texto": "Acrilização","descricao": "","icon": "event", "invert": true, "cor":"primary"},
{"id":"2","texto": "Ajuste ","descricao": "","icon": "event", "invert": true, "cor":"primary"},
{"id":"3","texto": "Análogo","descricao": "Análogo...","icon": "gavel", "invert": true, "cor":"secondary" },
{"id":"4","texto": "Aplicação ","descricao": "Aplicação... ","icon": "event", "invert": true, "cor":"primary"},
{"id":"5","texto": "Apoio","descricao": "Apoio...","icon": "http", "invert": true, "cor":"secondary" },
{"id":"6","texto": "Art Glass","descricao": "Art Glass...","icon": "event", "invert": true, "cor":"primary"},
{"id":"7","texto": "Barra ","descricao": "Barra... ","icon": "opacity", "invert": true, "cor":"secondary" },
{"id":"8","texto": "Capsula ","descricao": "Capsula... ","icon": "event", "invert": true, "cor":"primary"},
{"id":"9","texto": "Casquete ","descricao": "Casquete... ","icon": "pets", "invert": true, "cor":"secondary" },
{"id":"10","texto": "Cerâmica","descricao": "Cerâmica...","icon": "event", "invert": true, "cor":"primary"},
{"id":"11","texto": "Componentes","descricao": "Componentes...","icon": "redeem", "invert": true, "cor":"primary" },
{"id":"12","texto": "Coping ","descricao": "Coping... ","icon": "event", "invert": true, "cor":"primary"},
{"id":"13","texto": "Coroa","descricao": "Coroa...","icon": "event", "invert": true, "cor":"primary"},
{"id":"14","texto": "Devoluçao ","descricao": "Devoluçao... ","icon": "pets", "invert": true, "cor":"secondary" },
{"id":"15","texto": "Diversos","descricao": "Diversos...","icon": "event", "invert": true, "cor":"primary"},
{"id":"16","texto": "Duplicação de modelo","descricao": "Duplicação de modelo...","icon": "event", "invert": true, "cor":"primary"},
{"id":"17","texto": "Emax","descricao": "Emax...","icon": "event", "invert": true, "cor":"primary"},
{"id":"18","texto": "Encaixe","descricao": "Encaixe...","icon": "event", "invert": true, "cor":"primary"},
{"id":"19","texto": "Enceramento","descricao": "Enceramento...","icon": "event", "invert": true, "cor":"primary"},
{"id":"20","texto": "Enceramento diagnóstico","descricao": "Enceramento diagnóstico...","icon": "event", "invert": true, "cor":"primary"},
{"id":"21","texto": "Estrutura prótese Adesiva","descricao": "Estrutura prótese Adesiva...","icon": "event", "invert": true, "cor":"primary"},
{"id":"22","texto": "Estrutura ziconia ","descricao": "Estrutura ziconia... ","icon": "event", "invert": true, "cor":"primary"},
{"id":"23","texto": "Flexite","descricao": "Flexite...","icon": "event", "invert": true, "cor":"primary"},
{"id":"24","texto": "Gesso","descricao": "Gesso...","icon": "event", "invert": true, "cor":"primary"},
{"id":"25","texto": "Grampos","descricao": "Grampos...","icon": "event", "invert": true, "cor":"primary"},
{"id":"26","texto": "Guia cirúrgico","descricao": "Guia cirúrgico...","icon": "event", "invert": true, "cor":"primary"},
{"id":"27","texto": "Inceran","descricao": "Inceran...","icon": "event", "invert": true, "cor":"primary"},
{"id":"28","texto": "Lente contato","descricao": "Lente contato...","icon": "event", "invert": true, "cor":"primary"},
{"id":"29","texto": "Metal","descricao": "Metal...","icon": "event", "invert": true, "cor":"primary"},
{"id":"30","texto": "Métalo cerâmica","descricao": "Métalo cerâmica...","icon": "event", "invert": true, "cor":"primary"},
{"id":"31","texto": "Nota anterior","descricao": "Nota anterior...","icon": "event", "invert": true, "cor":"primary"},
{"id":"32","texto": "Over Denture","descricao": "Over Denture...","icon": "event", "invert": true, "cor":"primary"},
{"id":"34","texto": "Placa","descricao": "Placa...","icon": "event", "invert": true, "cor":"primary"},
{"id":"35","texto": "Plaquinha de dente Trilux","descricao": "Plaquinha de dente Trilux...","icon": "event", "invert": true, "cor":"primary"},
{"id":"36","texto": "Plaquinha dente Natus","descricao": "Plaquinha dente Natus...","icon": "event", "invert": true, "cor":"primary"},
{"id":"37","texto": "PPR","descricao": "PPR...","icon": "event", "invert": true, "cor":"primary"},
{"id":"38","texto": "Prótese","descricao": "Prótese...","icon": "event", "invert": true, "cor":"primary"},
{"id":"39","texto": "Protocolo","descricao": "Protocolo...","icon": "event", "invert": true, "cor":"primary"},
{"id":"40","texto": "Protocolo Cerâmico","descricao": "Protocolo Cerâmico...","icon": "event", "invert": true, "cor":"primary"},
{"id":"41","texto": "Provisório","descricao": "Provisório...","icon": "event", "invert": true, "cor":"primary"},
{"id":"42","texto": "PT","descricao": "PT","icon": "event", "invert": true, "cor":"primary"},
{"id":"43","texto": "Remontagem","descricao": "Remontagem...","icon": "event", "invert": true, "cor":"primary"},
{"id":"44","texto": "Removíveis","descricao": "Removíveis...","icon": "event", "invert": true, "cor":"primary"},
{"id":"45","texto": "Repetição coping","descricao": "Repetição coping...","icon": "event", "invert": true, "cor":"primary"},
{"id":"46","texto": "Repetir Moldagem","descricao": "Repetir Moldagem...","icon": "event", "invert": true, "cor":"primary"},
{"id":"47","texto": "Retirada porcelana","descricao": "Retirada porcelana...","icon": "event", "invert": true, "cor":"primary"},
{"id":"48","texto": "separar componentes","descricao": "separar componentes...","icon": "event", "invert": true, "cor":"primary"},
{"id":"49","texto": "Taxa urgência","descricao": "Taxa urgência...","icon": "event", "invert": true, "cor":"primary"},
{"id":"50","texto": "Troquelização","descricao": "Troquelização...","icon": "event", "invert": true, "cor":"primary"},
{"id":"51","texto": "Ucla","descricao": "Ucla...","icon": "event", "invert": true, "cor":"primary"},
{"id":"52","texto": "Visita","descricao": "Visita...","icon": "event", "invert": true, "cor":"primary"},
{"id":"53","texto": "Zirconia","descricao": "Zirconia...","icon": "event", "invert": true, "cor":"primary"}
]
